LICENSE
MANIFEST.in
README.md
RELEASE-VERSION
setup.py
version.py
debian/changelog
debian/compat
debian/control
debian/deadman.ini
debian/python3-zgres.dirs
debian/python3-zgres.install
debian/rules
debian/sync.ini
debian/zgres-deadman.dirs
debian/zgres-deadman.install
debian/zgres-deadman.service
debian/zgres-sync.dirs
debian/zgres-sync.install
debian/zgres-sync.service
debian/source/format
debian/source/options
zgres/__init__.py
zgres/apply.py
zgres/apt.py
zgres/config.py
zgres/deadman.py
zgres/ec2.py
zgres/plugin.py
zgres/replication.py
zgres/show.py
zgres/sync.py
zgres/systemd.py
zgres/utils.py
zgres/zookeeper.py
zgres.egg-info/PKG-INFO
zgres.egg-info/SOURCES.txt
zgres.egg-info/dependency_links.txt
zgres.egg-info/entry_points.txt
zgres.egg-info/top_level.txt
zgres.egg-info/zip-safe
zgres/tests/__init__.py
zgres/tests/test_apply.py
zgres/tests/test_apt.py
zgres/tests/test_config.py
zgres/tests/test_dcs.py
zgres/tests/test_deadman.py
zgres/tests/test_deadman_integration.py
zgres/tests/test_ec2.py
zgres/tests/test_plugin.py
zgres/tests/test_replication.py
zgres/tests/test_show.py
zgres/tests/test_systemd.py
zgres/tests/test_utils.py
zgres/tests/test_zookeeper.py