Metadata-Version: 1.0
Name: zgres
Version: 0.4
Summary: Database Connection and failover manager for PostgreSQL
Home-page: UNKNOWN
Author: UNKNOWN
Author-email: UNKNOWN
License: UNKNOWN
Platform: UNKNOWN
